iss_positioner/__init__.py
iss_positioner/calculations.py
iss_positioner/handlers.py
iss_positioner/log.py
iss_positioner/middlewares.py
iss_positioner/redis.py
iss_positioner/server.py
iss_positioner/tasks.py
iss_positioner/util.py
iss_positioner/html/index.html
iss_positioner/html/lst.html
iss_positioner-1.0.6.dist-info/DESCRIPTION.rst
iss_positioner-1.0.6.dist-info/METADATA
iss_positioner-1.0.6.dist-info/RECORD
iss_positioner-1.0.6.dist-info/WHEEL
iss_positioner-1.0.6.dist-info/metadata.json
iss_positioner-1.0.6.dist-info/top_level.txt
