Metadata-Version: 2.0
Name: iss-positioner
Version: 1.0.6
Summary: ISS position computing service
Home-page: https://github.com/nkoshell/iss-positioner
Author: nkoshell
Author-email: nikita.koshelev@gmail.com
License: MIT
Download-URL: https://github.com/nkoshell/iss-positioner/archive/1.0.6.tar.gz
Platform: UNKNOWN
Requires-Dist: aiohttp (>=2.2.0)
Requires-Dist: aioredis (>=0.3.1)
Requires-Dist: dateutils (>=0.6.6)
Requires-Dist: pyaml (>=16.12.2)
Requires-Dist: pyephem (>=3.7.6.0)
Requires-Dist: tqdm (>=4.14.0)
Requires-Dist: ujson (>=1.35)
